frameio_experimental/__init__.py
frameio_experimental/account_permissions/__init__.py
frameio_experimental/account_permissions/client.py
frameio_experimental/account_permissions/raw_client.py
frameio_experimental/accounts/__init__.py
frameio_experimental/accounts/client.py
frameio_experimental/accounts/raw_client.py
frameio_experimental/accounts/types/__init__.py
frameio_experimental/accounts/types/accounts_index_request_sort.py
frameio_experimental/client.py
frameio_experimental/collections/__init__.py
frameio_experimental/collections/client.py
frameio_experimental/collections/raw_client.py
frameio_experimental/comments/__init__.py
frameio_experimental/comments/client.py
frameio_experimental/comments/raw_client.py
frameio_experimental/comments/types/__init__.py
frameio_experimental/comments/types/comments_index_request_include.py
frameio_experimental/comments/types/comments_show_request_include.py
frameio_experimental/comments/types/create_comment_params_data.py
frameio_experimental/comments/types/update_comment_params_data.py
frameio_experimental/core/__init__.py
frameio_experimental/core/api_error.py
frameio_experimental/core/client_wrapper.py
frameio_experimental/core/datetime_utils.py
frameio_experimental/core/file.py
frameio_experimental/core/force_multipart.py
frameio_experimental/core/http_client.py
frameio_experimental/core/http_response.py
frameio_experimental/core/http_sse/__init__.py
frameio_experimental/core/http_sse/_api.py
frameio_experimental/core/http_sse/_decoders.py
frameio_experimental/core/http_sse/_exceptions.py
frameio_experimental/core/http_sse/_models.py
frameio_experimental/core/jsonable_encoder.py
frameio_experimental/core/pydantic_utilities.py
frameio_experimental/core/query_encoder.py
frameio_experimental/core/remove_none_from_dict.py
frameio_experimental/core/request_options.py
frameio_experimental/core/serialization.py
frameio_experimental/custom_actions/__init__.py
frameio_experimental/custom_actions/client.py
frameio_experimental-0.0.6.dist-info/METADATA
frameio_experimental-0.0.6.dist-info/WHEEL
frameio_experimental-0.0.6.dist-info/RECORD
